LICENSE
kkt/__init__.py
kkt/builders/__init__.py
kkt/builders/factory.py
kkt/builders/kernels/__init__.py
kkt/builders/kernels/bootstrap.py
kkt/builders/kernels/notebook_kernel.py
kkt/builders/kernels/script_kernel.py
kkt/builders/package.py
kkt/builders/packaging_system.py
kkt/cli.py
kkt/commands/__init__.py
kkt/commands/download.py
kkt/commands/init.py
kkt/commands/install.py
kkt/commands/kkt_command.py
kkt/commands/push.py
kkt/commands/status.py
kkt/exception.py
kkt/fetch.py
kkt/kernel_proc.py
kkt/parser.py
kkt/repo.py
kkt/resource.py
kkt/util.py
kkt-0.3.9.dist-info/entry_points.txt
kkt-0.3.9.dist-info/LICENSE
kkt-0.3.9.dist-info/WHEEL
kkt-0.3.9.dist-info/METADATA
kkt-0.3.9.dist-info/RECORD
