Metadata-Version: 2.1
Name: kkt
Version: 0.3.9
Summary: A tool for kaggle kernel
Home-page: https://github.com/ar90n/kkt
License: MIT
Keywords: kaggle
Author: Masahiro Wada
Author-email: argon.argon.argon@gmail.com
Requires-Python: >=3.7,<4.0
Classifier: Environment :: Console
Classifier: License :: OSI Approved :: MIT License
Classifier: Programming Language :: Python
Classifier: Programming Language :: Python :: 3
Classifier: Programming Language :: Python :: 3.7
Classifier: Programming Language :: Python :: 3.8
Classifier: Topic :: Software Development :: Libraries :: Python Modules
Requires-Dist: click (>=7.0,<8.0)
Requires-Dist: gitpython (>=3.1,<4.0)
Requires-Dist: kaggle (>=1.5,<2.0)
Requires-Dist: lockfile (>=0.12.2,<0.13.0)
Requires-Dist: poetry (==1.0.0)
Requires-Dist: tomlkit (>=0.5.8,<0.6.0)
Project-URL: Repository, https://github.com/ar90n/kkt
